[
  {
    "id": 1,
    "titulo": "O Futuro da IA",
    "descricao": "Uma análise aprofundada sobre as últimas inovações em IA e como elas moldarão o nosso futuro. Descubra os avanços em aprendizado de máquina e visão computacional.",
    "ano": "23/05/2025"
  },
  {
    "id": 2,
    "titulo": "É nesse naipe",
    "descricao": "Uma análise aprofundada sobre as últimas inovações em IA e como elas moldarão o nosso futuro. Descubra os avanços em aprendizado de máquina e visão computacional.",
    "ano": "25/05/2025"
  }
]